fastlz5.cp39-win_amd64.pyd
fastlz5-0.0.1.4.dist-info/METADATA
fastlz5-0.0.1.4.dist-info/WHEEL
fastlz5-0.0.1.4.dist-info/top_level.txt
fastlz5-0.0.1.4.dist-info/RECORD
